tachi_local/__init__.py
tachi_local/__main__.py
tachi_local/cmdline_parser.py
tachi_local/main.py
tachi_local/manga.py
tachi_local/manga_to_json.py
tachi_local/version.py
tachi_local/bakaupdates/__init__.py
tachi_local/bakaupdates/scraper.py
tachi_local/bakaupdates/searcher.py
tachi_local/bakaupdates/utils.py
tachi_local-1.2.1.dist-info/licenses/LICENSE
tachi_local-1.2.1.dist-info/METADATA
tachi_local-1.2.1.dist-info/WHEEL
tachi_local-1.2.1.dist-info/entry_points.txt
tachi_local-1.2.1.dist-info/top_level.txt
tachi_local-1.2.1.dist-info/RECORD
